infogenomics/__init__.py
infogenomics-0.5.dist-info/LICENSE
infogenomics-0.5.dist-info/METADATA
infogenomics-0.5.dist-info/WHEEL
infogenomics-0.5.dist-info/top_level.txt
infogenomics-0.5.dist-info/RECORD
