Metadata-Version: 2.1
Name: infogenomics
Version: 0.5
Summary: Advanced framework for the informational genomics in python3
Home-page: https://github.com/MassimilianoLoss/Frmw_4_Informational_genomics.git
Author: Vincenzo Bonnici, Massimiliano Loss
Author-email: vincenzo.bonnici@univr.it, massimiliano.loss@studenti.univr.it
License: UNKNOWN
Platform: UNKNOWN
Classifier: Programming Language :: Python :: 3
Classifier: License :: OSI Approved :: MIT License
Classifier: Operating System :: OS Independent
